pexels_async_api
tests
