Metadata-Version: 2.1
Name: pexels-async-api
Version: 0.2
Summary: An Asynchronous Python Client for the Pexels API
Home-page: https://github.com/darkcurrent/pexels_async_api
Author: Cagin Polat
Author-email: caginpolat@notrino.com
Classifier: Programming Language :: Python :: 3
Classifier: License :: OSI Approved :: MIT License
Classifier: Operating System :: OS Independent
Requires-Python: >=3.6
License-File: LICENSE
